dictsqlite/__init__.py
dictsqlite/_native.abi3.so
dictsqlite/modules/__init__.py
dictsqlite/modules/safe_pickle.py
dictsqlite-2.0.9.dist-info/METADATA
dictsqlite-2.0.9.dist-info/WHEEL
dictsqlite-2.0.9.dist-info/RECORD
