Metadata-Version: 2.4
Name: dictsqlite
Version: 2.0.9
Classifier: License :: OSI Approved :: MIT License
Classifier: Development Status :: 4 - Beta
Classifier: Operating System :: OS Independent
Classifier: Intended Audience :: Developers
Classifier: Programming Language :: Python :: 3
Classifier: Programming Language :: Python :: 3.9
Classifier: Programming Language :: Python :: 3.10
Classifier: Programming Language :: Python :: 3.11
Classifier: Programming Language :: Python :: 3.12
Requires-Dist: msgpack>=1.0.0
Summary: High-performance DictSQLite v2 with I/O optimizations
Author-email: Disnana <support@disnana.com>
License: MIT
Requires-Python: >=3.9
